ollama_panongbene-0.1.0.dist-info/licenses/LICENSE
ollama_toolkit/__init__.py
ollama_toolkit/cli.py
ollama_toolkit/export.py
ollama_toolkit/import_.py
tests/__init__.py
tests/test_export.py
tests/test_import.py
ollama_panongbene-0.1.0.dist-info/METADATA
ollama_panongbene-0.1.0.dist-info/WHEEL
ollama_panongbene-0.1.0.dist-info/entry_points.txt
ollama_panongbene-0.1.0.dist-info/top_level.txt
ollama_panongbene-0.1.0.dist-info/RECORD
