Metadata-Version: 2.4
Name: ollama-panongbene
Version: 0.1.0
Summary: CLI tools to export and import Ollama models (.tar.gz)
Author: Panongbene Sawadogo
Author-email: Panongbene Sawadogo <amet1900@gmail.com>
Requires-Python: >=3.7
License-File: LICENSE
Requires-Dist: tqdm
Dynamic: author
Dynamic: license-file
Dynamic: requires-python
